{
  "scores": [
    {
      "score": 2495,
      "name": "Player",
      "date": "2026-01-01T04:55:56.487203",
      "stats": {
        "total_jumps": 26,
        "double_jumps": 24,
        "helicopter_uses": 5,
        "platforms_landed": 36,
        "collectibles_gathered": 18,
        "max_combo": 36,
        "distance_traveled": 17882,
        "play_time": 38.38333333333244
      }
    },
    {
      "score": 985,
      "name": "Player",
      "date": "2025-12-31T16:53:14.970816",
      "stats": {
        "total_jumps": 12,
        "double_jumps": 27,
        "helicopter_uses": 14,
        "platforms_landed": 29,
        "collectibles_gathered": 11,
        "max_combo": 9,
        "distance_traveled": 23172,
        "play_time": 51.99999999999833
      }
    },
    {
      "score": 900,
      "name": "Player",
      "date": "2026-01-01T19:50:15.503634",
      "stats": {
        "total_jumps": 12,
        "double_jumps": 8,
        "helicopter_uses": 2,
        "platforms_landed": 12,
        "collectibles_gathered": 4,
        "max_combo": 12,
        "distance_traveled": 5437,
        "play_time": 12.466666666666866,
        "max_difficulty_reached": 1.2077777777777812,
        "total_platforms_landed": 203
      }
    },
    {
      "score": 870,
      "name": "Player",
      "date": "2026-01-01T09:10:58.024644",
      "stats": {
        "total_jumps": 9,
        "double_jumps": 23,
        "helicopter_uses": 7,
        "platforms_landed": 15,
        "collectibles_gathered": 65,
        "max_combo": 6,
        "distance_traveled": 14989,
        "play_time": 32.38333333333278
      }
    },
    {
      "score": 865,
      "name": "Player",
      "date": "2025-12-31T16:50:46.242208",
      "stats": {
        "total_jumps": 14,
        "double_jumps": 27,
        "helicopter_uses": 13,
        "platforms_landed": 20,
        "collectibles_gathered": 54,
        "max_combo": 5,
        "distance_traveled": 18191,
        "play_time": 40.08333333333234
      }
    },
    {
      "score": 855,
      "name": "Player",
      "date": "2026-01-01T04:53:20.170421",
      "stats": {
        "total_jumps": 12,
        "double_jumps": 19,
        "helicopter_uses": 3,
        "platforms_landed": 18,
        "collectibles_gathered": 24,
        "max_combo": 18,
        "distance_traveled": 9710,
        "play_time": 21.06666666666675
      }
    },
    {
      "score": 855,
      "name": "Player",
      "date": "2026-01-01T19:46:32.401843",
      "stats": {
        "total_jumps": 6,
        "double_jumps": 14,
        "helicopter_uses": 12,
        "platforms_landed": 15,
        "collectibles_gathered": 45,
        "max_combo": 9,
        "distance_traveled": 15638,
        "play_time": 34.51666666666599,
        "max_difficulty_reached": 1.5752777777777665,
        "total_platforms_landed": 52
      }
    },
    {
      "score": 845,
      "name": "Player",
      "date": "2026-01-01T19:49:56.421405",
      "stats": {
        "total_jumps": 10,
        "double_jumps": 11,
        "helicopter_uses": 6,
        "platforms_landed": 16,
        "collectibles_gathered": 13,
        "max_combo": 16,
        "distance_traveled": 8785,
        "play_time": 17.68333333333361,
        "max_difficulty_reached": 1.2947222222222268,
        "total_platforms_landed": 188
      }
    },
    {
      "score": 810,
      "name": "Player",
      "date": "2026-01-01T19:50:50.531292",
      "stats": {
        "total_jumps": 18,
        "double_jumps": 22,
        "helicopter_uses": 5,
        "platforms_landed": 23,
        "collectibles_gathered": 36,
        "max_combo": 13,
        "distance_traveled": 14871,
        "play_time": 33.1999999999994,
        "max_difficulty_reached": 1.5533333333333235,
        "total_platforms_landed": 226
      }
    },
    {
      "score": 740,
      "name": "Player",
      "date": "2026-01-01T19:51:31.849607",
      "stats": {
        "total_jumps": 7,
        "double_jumps": 17,
        "helicopter_uses": 6,
        "platforms_landed": 20,
        "collectibles_gathered": 13,
        "max_combo": 11,
        "distance_traveled": 12074,
        "play_time": 26.94999999999975,
        "max_difficulty_reached": 1.4491666666666625,
        "total_platforms_landed": 246
      }
    }
  ],
  "customization": {
    "player_theme": "classic",
    "platform_theme": "grass",
    "background_theme": "forest"
  },
  "last_updated": "2026-01-01T19:51:31.849655"
}